{
  "name": "Agreement",
  "base": "PersistedModel",
  "idInjection": true,
  "options": {
    "validateUpsert": true
  },
  "properties": {
    "pickup_station": {
      "type": "number"
    },
    "dropoff_station": {
      "type": "number",
      "required": true
    },
    "datetime": {
      "type": "date",
      "required": true
    },
    "delivered": {
      "type": "boolean",
      "required": true
    }
  },
  "validations": [],
  "relations": {
    "user": {
      "type": "belongsTo",
      "model": "user",
      "foreignKey": ""
    }
  },
  "acls": [],
  "methods": {}
}
